design/source/Core.v
module Core #(
        parameter ROWS = 64,
        parameter COLS = 64,
        parameter ROWS_ADDR_WIDTH = 6,
        parameter COLS_ADDR_WIDTH = 6,
        parameter BRAM_ADDR_WIDTH = ROWS_ADDR_WIDTH + COLS_ADDR_WIDTH
    ) (
        input clk,
        input rstn,
        output [BRAM_ADDR_WIDTH-1:0] bram_rd_addr,
        input [7:0] bram_rd_data,
        input detect_start,
        output detect_finish,
        output [2:0] detect_peak_num,
        input [2:0] disp_peak_idx,
        output [ROWS_ADDR_WIDTH-1:0] disp_peak_row,
        output [COLS_ADDR_WIDTH-1:0] disp_peak_col,
        output [7:0] disp_peak_val
    );

    parameter PADDING = 2;
    parameter EXT_ROWS = ROWS + 2 * PADDING;
    parameter EXT_COLS = COLS + 2 * PADDING;

    parameter S_IDLE = 2'b00;
    parameter S_ISSUING = 2'b01;
    parameter S_DRAIN = 2'b10;
    parameter S_DONE = 2'b11;
    reg [1:0] state = S_IDLE;

    reg [ROWS_ADDR_WIDTH:0] ext_row = 0;
    reg [COLS_ADDR_WIDTH:0] ext_col = 0;
    wire vld = (ext_row >= 2) && (ext_row <= 65) && (ext_col >= 2) && (ext_col <= 65);
    wire [ROWS_ADDR_WIDTH-1:0] real_row = ext_row - 2;
    wire [COLS_ADDR_WIDTH-1:0] real_col = ext_col - 2;

    // 发射系统
    wire [BRAM_ADDR_WIDTH-1:0] issue_addr = vld ? {real_row, real_col} : 0;
    assign bram_rd_addr = issue_addr;

    // 延迟量定义
    wire issue_a_value = state == S_ISSUING;
    reg issue_a_value_d1 = 0;
    reg issue_a_value_d2 = 0;
    reg eval_vld = 0;
    reg vld_d1 = 0;
    reg vld_d2 = 0;
    reg [ROWS_ADDR_WIDTH:0] ext_row_d1 = 0;
    reg [COLS_ADDR_WIDTH:0] ext_col_d2 = 0;
    reg [COLS_ADDR_WIDTH:0] ext_col_d1 = 0;
    reg [ROWS_ADDR_WIDTH:0] ext_row_d2 = 0;
    reg [ROWS_ADDR_WIDTH-1:0] center_row_d3 = 0;
    reg [COLS_ADDR_WIDTH-1:0] center_col_d3 = 0;

    // 行缓存定义
    reg [7:0] line_buf0 [0:EXT_COLS-1]; // 不需要初始化，因为只要对应的line_vld_buf是0，win的值就不影响结果
    reg [7:0] line_buf1 [0:EXT_COLS-1];
    reg [7:0] line_buf2 [0:EXT_COLS-1];
    reg [7:0] line_buf3 [0:EXT_COLS-1];
    reg line_vld_buf0 [0:EXT_COLS-1];
    reg line_vld_buf1 [0:EXT_COLS-1];
    reg line_vld_buf2 [0:EXT_COLS-1];
    reg line_vld_buf3 [0:EXT_COLS-1];

    // 窗口定义
    reg [7:0] win [0:4][0:4]; // 不需要初始化，因为只要对应的win_vld是0，win的值就不影响结果
    reg win_vld [0:4][0:4];

    // 判断是否是峰值
    reg is_peak = 0;
    reg [11:0] outer_sum;
    reg [4:0] outer_vld_cnt;
    reg [31:0] lhs;
    reg [31:0] rhs;
    integer i, j;
    always @(*) begin
        is_peak = 1;
        outer_sum = 0;
        outer_vld_cnt = 0;
        lhs = 0;
        rhs = 0;

        for (i = 0; i <= 4; i = i + 1) begin
            for (j = 0; j <= 4; j = j + 1) begin
                if ((i != 2) || (j != 2)) begin
                    if (win_vld[i][j] && (win[i][j] >= win[2][2])) begin
                        is_peak = 0;
                    end
                end
            end
        end

        for (i = 0; i <= 4; i = i + 1) begin
            for (j = 0; j <= 4; j = j + 1) begin
                if ((i == 0 || i == 4 || j == 0 || j == 4) && win_vld[i][j]) begin
                    outer_sum = outer_sum + win[i][j];
                    outer_vld_cnt = outer_vld_cnt + 1;
                end
            end
        end

        // lhs和rhs是必须的，因为直接比较会溢出
        lhs = outer_vld_cnt * win[2][2];
        rhs = 2 * outer_sum;
        if (outer_vld_cnt > 0 && lhs <= rhs) begin
            is_peak = 0;
        end
    end
    wire is_peak_real = is_peak && win_vld[2][2] && eval_vld; // 只有当中心值有效、满足峰值条件、曾经没被算过是不是峰值时，才认为是一个真正的峰值

    // 判断插入位置
    reg [2:0] peak_num = 0;
    assign detect_peak_num = peak_num;
    reg [7:0] peak_vals [0:5];
    reg [ROWS_ADDR_WIDTH-1:0] peak_rows [0:5];
    reg [COLS_ADDR_WIDTH-1:0] peak_cols [0:5];
    reg do_insert = 0;
    reg [2:0] insert_pos = 3'd7; // 不插入时默认为7
    always @(*) begin
        do_insert = 0;
        insert_pos = 3'd7; // 默认不插入

        if (is_peak_real) begin
            if (win[2][2] > peak_vals[0]) begin
                do_insert = 1;
                insert_pos = 0;
            end
            else if (win[2][2] > peak_vals[1]) begin
                do_insert = 1;
                insert_pos = 1;
            end
            else if (win[2][2] > peak_vals[2]) begin
                do_insert = 1;
                insert_pos = 2;
            end
            else if (win[2][2] > peak_vals[3]) begin
                do_insert = 1;
                insert_pos = 3;
            end
            else if (win[2][2] > peak_vals[4]) begin
                do_insert = 1;
                insert_pos = 4;
            end
            else if (win[2][2] > peak_vals[5]) begin
                do_insert = 1;
                insert_pos = 5;
            end
            else begin
                do_insert = 0;
                insert_pos = 7;
            end
        end
    end

    // 时序逻辑：延、进、移、插、迭
    /*
        状态机只管“发不发地址”和“什么时候结束”
        延迟管道只管“地址/valid 和 BRAM data 对齐”
        pix_cycle 只管“窗口何时移动”
        eval_valid 只管“何时检测窗口”
        do_insert 只管“何时更新 Top-6”
    */
    integer m, n;
    integer k;
    always @(posedge clk) begin
        // 延迟管道更新
        if (state == S_ISSUING || state == S_DRAIN) begin
            issue_a_value_d1 <= issue_a_value;
            issue_a_value_d2 <= issue_a_value_d1;
            eval_vld <= issue_a_value_d2;
            vld_d1 <= vld;
            vld_d2 <= vld_d1;
            ext_row_d1 <= ext_row;
            ext_row_d2 <= ext_row_d1;
            center_row_d3 <= ext_row_d2 - 4;
            ext_col_d1 <= ext_col;
            ext_col_d2 <= ext_col_d1;
            center_col_d3 <= ext_col_d2 - 4;
        end

        // 数据流动
        if (issue_a_value_d2) begin
            // 新的数据进入窗口
            win[4][4] <= vld_d2 ? bram_rd_data : 0;
            win_vld[4][4] <= vld_d2;

            // 窗口和行缓存移动
            line_buf0[ext_col_d2] <= vld_d2 ? bram_rd_data : 0;
            line_buf1[ext_col_d2] <= line_buf0[ext_col_d2];
            line_buf2[ext_col_d2] <= line_buf1[ext_col_d2];
            line_buf3[ext_col_d2] <= line_buf2[ext_col_d2];

            line_vld_buf0[ext_col_d2] <= vld_d2;
            line_vld_buf1[ext_col_d2] <= line_vld_buf0[ext_col_d2];
            line_vld_buf2[ext_col_d2] <= line_vld_buf1[ext_col_d2];
            line_vld_buf3[ext_col_d2] <= line_vld_buf2[ext_col_d2];

            for (m = 0; m <= 4; m = m + 1) begin
                for (n = 0; n <= 3; n = n + 1) begin
                    win[m][n] <= win[m][n+1];
                    win_vld[m][n] <= win_vld[m][n+1];
                end
            end

            win[0][4] <= line_buf3[ext_col_d2];
            win[1][4] <= line_buf2[ext_col_d2];
            win[2][4] <= line_buf1[ext_col_d2];
            win[3][4] <= line_buf0[ext_col_d2];

            win_vld[0][4] <= line_vld_buf3[ext_col_d2];
            win_vld[1][4] <= line_vld_buf2[ext_col_d2];
            win_vld[2][4] <= line_vld_buf1[ext_col_d2];
            win_vld[3][4] <= line_vld_buf0[ext_col_d2];
        end

        // 峰值插入
        if (do_insert) begin
            if (peak_num < 6) begin // 这个判断是必须的，万一peak_num已经满了但新来的值又比第6大的话，peak_num还在加，就爆了
                peak_num <= peak_num + 1;
            end

            for (k = 5; k > 0; k = k - 1) begin
                if (k > insert_pos) begin
                    peak_vals[k] <= peak_vals[k-1];
                    peak_rows[k] <= peak_rows[k-1];
                    peak_cols[k] <= peak_cols[k-1];
                end
            end
            peak_vals[insert_pos] <= win[2][2];
            peak_rows[insert_pos] <= center_row_d3;
            peak_cols[insert_pos] <= center_col_d3;
        end

        // 状态机
        case (state)
            S_ISSUING: begin
                // 坐标迭代（只在S_ISSUING状态下进行）
                if (ext_row == EXT_ROWS - 1 && ext_col == EXT_COLS - 1) begin
                    state <= S_DRAIN;
                end
                else begin
                    if (ext_col == EXT_COLS - 1) begin
                        ext_row <= ext_row + 1;
                        ext_col <= 0;
                    end
                    else begin
                        ext_col <= ext_col + 1;
                    end
                end
            end

            S_DRAIN: begin
                // 如果是在S_DRAIN状态，不迭代坐标，等待缓冲区数据排空即可
                if (state == S_DRAIN) begin
                    if (issue_a_value_d1 == 0 && issue_a_value_d2 == 0 && eval_vld == 0) begin
                        state <= S_DONE;
                    end
                end
            end

            S_DONE: begin
                // 检测完成，在S_DONE停留直到detect_start拉低，之后回到S_IDLE展示结果及等待下一次检测
                if (detect_start == 0) begin
                    state <= S_IDLE;
                end
            end

            S_IDLE: begin
                // S_IDLE状态下，清空虚拟坐标 延迟量
                ext_row <= 0;
                ext_col <= 0;
                issue_a_value_d1 <= 0;
                issue_a_value_d2 <= 0;
                eval_vld <= 0;
                vld_d1 <= 0;
                vld_d2 <= 0;
                ext_row_d1 <= 0;
                ext_row_d2 <= 0;
                ext_col_d1 <= 0;
                ext_col_d2 <= 0;

                if (detect_start) begin
                    // 下一次检测开始前，清空peak_num peak_vals peak_rows peak_cols line_vld_buf win_vld
                    // TODO: 复用m可能有bug，需要验证
                    for (m = 0; m <= EXT_COLS-1; m = m + 1) begin
                        line_vld_buf0[m] <= 0;
                        line_vld_buf1[m] <= 0;
                        line_vld_buf2[m] <= 0;
                        line_vld_buf3[m] <= 0;
                    end
                    for (m = 0; m <= 4; m = m + 1) begin
                        for (n = 0; n <= 4; n = n + 1) begin
                            win_vld[m][n] <= 0;
                        end
                    end

                    peak_num <= 0;
                    for (m = 0; m <= 5; m = m + 1) begin
                        peak_vals[m] <= 0;
                        peak_rows[m] <= 0;
                        peak_cols[m] <= 0;
                    end

                    state <= S_ISSUING;
                end
            end
        endcase

        if (rstn == 0) begin
            // rstn触发时，回到S_IDLE状态，并清空虚拟坐标 延迟量 peak_num peak_vals peak_rows peak_cols line_vld_buf win_vld
            state <= S_IDLE;

            ext_row <= 0;
            ext_col <= 0;
            issue_a_value_d1 <= 0;
            issue_a_value_d2 <= 0;
            eval_vld <= 0;
            vld_d1 <= 0;
            vld_d2 <= 0;
            ext_row_d1 <= 0;
            ext_row_d2 <= 0;
            ext_col_d1 <= 0;
            ext_col_d2 <= 0;

            for (m = 0; m <= EXT_COLS-1; m = m + 1) begin
                line_vld_buf0[m] <= 0;
                line_vld_buf1[m] <= 0;
                line_vld_buf2[m] <= 0;
                line_vld_buf3[m] <= 0;
            end
            for (m = 0; m <= 4; m = m + 1) begin
                for (n = 0; n <= 4; n = n + 1) begin
                    win_vld[m][n] <= 0;
                end
            end

            peak_num <= 0;
            for (m = 0; m <= 5; m = m + 1) begin
                peak_vals[m] <= 0;
                peak_rows[m] <= 0;
                peak_cols[m] <= 0;
            end
        end
    end

    assign detect_finish = (state == S_DONE);

    // 输出系统
    reg [ROWS_ADDR_WIDTH-1:0] disp_peak_row_reg;
    reg [COLS_ADDR_WIDTH-1:0] disp_peak_col_reg;
    reg [7:0] disp_peak_val_reg;
    assign disp_peak_col = disp_peak_col_reg;
    assign disp_peak_row = disp_peak_row_reg;
    assign disp_peak_val = disp_peak_val_reg;
    always @(*) begin
        if (disp_peak_idx < peak_num) begin
            disp_peak_row_reg = peak_rows[disp_peak_idx];
            disp_peak_col_reg = peak_cols[disp_peak_idx];
            disp_peak_val_reg = peak_vals[disp_peak_idx];
        end
        else begin
            disp_peak_row_reg = 0;
            disp_peak_col_reg = 0;
            disp_peak_val_reg = 0;
        end
    end
endmodule

design/sim/tb_Core_page3_tmp.v
`timescale 1ns/1ns

module tb_Core();

    // BRAM大小（字节）
    parameter BRAM_SIZE = 4096;
    parameter BRAM_ADDR_WIDTH = 12;  // 2^12 = 4096
    parameter ROWS = 64;
    parameter COLS = 64;

    // 时钟和复位信号
    reg         clk;
    reg         rstn;

    // BRAM 接口
    wire [BRAM_ADDR_WIDTH-1:0]  bram_rd_addr;
    reg  [7:0]  bram_rd_data;

    // 检测控制信号
    reg         detect_start;
    wire        detect_finish;

    // 检测结果信号
    wire [2:0]  detect_peak_num;
    reg  [2:0]  disp_peak_idx;
    wire [BRAM_ADDR_WIDTH/2-1:0]  disp_peak_row;
    wire [BRAM_ADDR_WIDTH/2-1:0]  disp_peak_col;
    wire [7:0]  disp_peak_val;

    // 测试 BRAM
    integer     i;
    reg [7:0]   bram_mem [0:(BRAM_SIZE-1)];

    // 实例化被测模块
    Core u_Core (
             .clk            (clk),
             .rstn           (rstn),
             .bram_rd_addr   (bram_rd_addr),
             .bram_rd_data   (bram_rd_data),
             .detect_start   (detect_start),
             .detect_finish  (detect_finish),
             .detect_peak_num(detect_peak_num),
             .disp_peak_idx  (disp_peak_idx),
             .disp_peak_row  (disp_peak_row),
             .disp_peak_col  (disp_peak_col),
             .disp_peak_val  (disp_peak_val)
         );

    // 时钟生成
    always #10 clk = ~clk;  // 50MHz时钟
    // always #1 clk = ~clk;  // 500MHz时钟

    // BRAM读取模拟（1个时钟周期延迟）
    reg [BRAM_ADDR_WIDTH-1:0] bram_addr_delayed;
    reg [7:0] bram_data_delayed;

    always @(posedge clk) begin
        if (~rstn) begin
            bram_addr_delayed <= {BRAM_ADDR_WIDTH{1'b0}};
            bram_data_delayed <= 8'b0;
        end
        else begin
            bram_addr_delayed <= bram_rd_addr;
            bram_data_delayed <= bram_mem[bram_rd_addr];
        end
    end

    always @(*) begin
        bram_rd_data = bram_data_delayed;
    end

    // 测试流程
    initial begin
        // 初始化
        initialize();

        // 复位系统
        reset_system();

        // 加载BRAM数据
        load_bram_data();

        // 开始检测
        start_detection();

        // 显示检测结果
        display_results();

        // 结束测试
        #100;
        $display("Test completed successfully!");
        $finish;
    end

    // 初始化任务
    task initialize;
        begin
            clk = 0;
            rstn = 0;
            detect_start = 0;
            disp_peak_idx = 0;

            // 初始化BRAM内存为0
            for (i = 0; i < BRAM_SIZE; i = i + 1) begin
                bram_mem[i] = 8'h00;
            end
        end
    endtask

    // 系统复位任务
    task reset_system;
        begin
            #20;
            rstn = 1;
            #50;
            $display("System reset completed at time %t", $time);
        end
    endtask

    // 加载BRAM数据任务
    task load_bram_data;
        integer file, temp;
        begin
            // 从hex文件读取数据
            if (BRAM_SIZE == 1024) begin
                $display("Loading BRAM data from bram_32x32.dat...");
                file = $fopen("bram_32x32.dat", "r");
            end
            else if (BRAM_SIZE == 4096) begin
                $display("Loading BRAM data from bram_64x64_page3_tmp.dat...");
                file = $fopen("bram_64x64_page3_tmp.dat", "r");
            end
            else begin
                $display("Error: Unsupported BRAM_SIZE %d", BRAM_SIZE);
                $finish;
            end
            if (!file) begin
                $display("Error: Cannot open bram file!");
                $finish;
            end

            i = 0;
            while (!$feof(file) && i < BRAM_SIZE) begin
                temp = $fscanf(file, "%h", bram_mem[i]);
                // $display("BRAM LOAD =0x%h (%d, %d), data=0x%h (%d)",
                //             i[BRAM_ADDR_WIDTH-1:0], i[BRAM_ADDR_WIDTH-1:BRAM_ADDR_WIDTH/2], i[BRAM_ADDR_WIDTH/2-1:0], bram_mem[i], bram_mem[i]);
                i = i + 1;
            end
            $fclose(file);

            $display("BRAM data loaded successfully, %0d bytes read", i);
        end
    endtask

    // 开始检测任务
    task start_detection;
        begin
            #100;
            @(posedge clk) #1 detect_start = 1;
            $display("Detection started at time %t", $time);

            // 保持start信号为高直到检测完成
            while (!detect_finish) begin
                @(posedge clk);
            end
            @(posedge clk) #1 detect_start = 0;
            $display("Detection finished at time %t", $time);
            #100;
        end
    endtask

    // 显示结果任务
    task display_results;
        integer j;
        begin
            $display("\n=== Detection Results ===");
            $display("Number of peaks detected: %0d", detect_peak_num);

            if (detect_peak_num > 0) begin
                for (j = 0; j < detect_peak_num; j = j + 1) begin
                    @(posedge clk) disp_peak_idx = j;
                    #10;  // 等待输出稳定
                    $display("Peak[%0d]: Row=%d, Col=%d, Value=%d",
                             j, disp_peak_row, disp_peak_col, disp_peak_val);
                end
            end
            else begin
                $display("No peaks detected.");
            end

            $display("=== End of Results ===\n");
        end
    endtask

    // 监控关键信号
    always @(posedge clk) begin
        if (detect_start && !detect_finish) begin
            // 在检测过程中监控BRAM访问
            if (bram_rd_addr !== bram_addr_delayed) begin
                $display("Time %t: BRAM read address=0x%h (%d, %d), data=0x%h (%d)",
                         $time, bram_rd_addr, bram_rd_addr[BRAM_ADDR_WIDTH-1:BRAM_ADDR_WIDTH/2], bram_rd_addr[BRAM_ADDR_WIDTH/2-1:0], bram_mem[bram_rd_addr], bram_mem[bram_rd_addr]);
            end
        end
    end

    // 断言检查
    always @(posedge clk) begin
        if (rstn && detect_start) begin
            // 检查BRAM地址是否在有效范围内
            if (bram_rd_addr > (BRAM_SIZE-1)) begin
                $display("Warning: BRAM address out of range: 0x%h", bram_rd_addr);
            end
        end
    end

    initial begin
        $dumpfile("tb_Core.vcd");
        $dumpvars;
    end

    initial begin
        #100_000_000 $display("Test timeout!");
        $finish; // 超时保护
    end

endmodule

design/sim/tb_Core.vcd
$date
	Fri May 22 21:35:56 2026
$end
$version
	Icarus Verilog
$end
$timescale
	1ns
$end
$scope module tb_Core $end
$var wire 8 ! disp_peak_val [7:0] $end
$var wire 6 " disp_peak_row [5:0] $end
$var wire 6 # disp_peak_col [5:0] $end
$var wire 3 $ detect_peak_num [2:0] $end
$var wire 1 % detect_finish $end
$var wire 12 & bram_rd_addr [11:0] $end
$var parameter 32 ' BRAM_ADDR_WIDTH $end
$var parameter 32 ( BRAM_SIZE $end
$var parameter 32 ) COLS $end
$var parameter 32 * ROWS $end
$var reg 12 + bram_addr_delayed [11:0] $end
$var reg 8 , bram_data_delayed [7:0] $end
$var reg 8 - bram_rd_data [7:0] $end
$var reg 1 . clk $end
$var reg 1 / detect_start $end
$var reg 3 0 disp_peak_idx [2:0] $end
$var reg 1 1 rstn $end
$var integer 32 2 i [31:0] $end
$scope module u_Core $end
$var wire 12 3 bram_rd_addr [11:0] $end
$var wire 8 4 bram_rd_data [7:0] $end
$var wire 1 . clk $end
$var wire 3 5 detect_peak_num [2:0] $end
$var wire 1 / detect_start $end
$var wire 6 6 disp_peak_col [5:0] $end
$var wire 3 7 disp_peak_idx [2:0] $end
$var wire 6 8 disp_peak_row [5:0] $end
$var wire 8 9 disp_peak_val [7:0] $end
$var wire 1 : is_peak_real $end
$var wire 1 1 rstn $end
$var wire 1 ; vld $end
$var wire 6 < real_row [5:0] $end
$var wire 6 = real_col [5:0] $end
$var wire 12 > issue_addr [11:0] $end
$var wire 1 ? issue_a_value $end
$var wire 1 % detect_finish $end
$var parameter 33 @ BRAM_ADDR_WIDTH $end
$var parameter 32 A COLS $end
$var parameter 32 B COLS_ADDR_WIDTH $end
$var parameter 65 C EXT_COLS $end
$var parameter 65 D EXT_ROWS $end
$var parameter 32 E PADDING $end
$var parameter 32 F ROWS $end
$var parameter 32 G ROWS_ADDR_WIDTH $end
$var parameter 2 H S_DONE $end
$var parameter 2 I S_DRAIN $end
$var parameter 2 J S_IDLE $end
$var parameter 2 K S_ISSUING $end
$var reg 6 L center_col_d3 [5:0] $end
$var reg 6 M center_row_d3 [5:0] $end
$var reg 6 N disp_peak_col_reg [5:0] $end
$var reg 6 O disp_peak_row_reg [5:0] $end
$var reg 8 P disp_peak_val_reg [7:0] $end
$var reg 1 Q do_insert $end
$var reg 1 R eval_vld $end
$var reg 7 S ext_col [6:0] $end
$var reg 7 T ext_col_d1 [6:0] $end
$var reg 7 U ext_col_d2 [6:0] $end
$var reg 7 V ext_row [6:0] $end
$var reg 7 W ext_row_d1 [6:0] $end
$var reg 7 X ext_row_d2 [6:0] $end
$var reg 3 Y insert_pos [2:0] $end
$var reg 1 Z is_peak $end
$var reg 1 [ issue_a_value_d1 $end
$var reg 1 \ issue_a_value_d2 $end
$var reg 32 ] lhs [31:0] $end
$var reg 12 ^ outer_sum [11:0] $end
$var reg 5 _ outer_vld_cnt [4:0] $end
$var reg 3 ` peak_num [2:0] $end
$var reg 32 a rhs [31:0] $end
$var reg 2 b state [1:0] $end
$var reg 1 c vld_d1 $end
$var reg 1 d vld_d2 $end
$var integer 32 e i [31:0] $end
$var integer 32 f j [31:0] $end
$var integer 32 g k [31:0] $end
$var integer 32 h m [31:0] $end
$var integer 32 i n [31:0] $end
$upscope $end
$scope task display_results $end
$var integer 32 j j [31:0] $end
$upscope $end
$scope task initialize $end
$upscope $end
$scope task load_bram_data $end
$var integer 32 k file [31:0] $end
$var integer 32 l temp [31:0] $end
$upscope $end
$scope task reset_system $end
$upscope $end
$scope task start_detection $end
$upscope $end
$upscope $end
$enddefinitions $end
$comment Show the parameter values. $end
$dumpall
b1 K
b0 J
b10 I
b11 H
b110 G
b1000000 F
b10 E
b1000100 D
b1000100 C
b110 B
b1000000 A
b1100 @
b1000000 *
b1000000 )
b1000000000000 (
b1100 '
$end
#0
$dumpvars
bx l
bx k
bx j
bx i
bx h
bx g
bx f
bx e
0d
0c
b0 b
bx a
b0 `
bx _
bx ^
bx ]
0\
0[
0Z
b111 Y
b0 X
b0 W
b0 V
b0 U
b0 T
b0 S
0R
0Q
b0 P
b0 O
b0 N
b0 M
b0 L
0?
b0 >
b111110 =
b111110 <
0;
0:
b0 9
b0 8
b0 7
b0 6
b0 5
bx 4
b0 3
b1000000000000 2
01
b0 0
0/
0.
bx -
bx ,
bx +
b0 &
0%
b0 $
b0 #
b0 "
b0 !
$end
#10
b101 f
b101 e
b0 a
bx ]
b0 _
b0 ^
1Z
b0 -
b0 4
b0 ,
b0 +
b101 i
b110 h
1.
#20
0.
11
#30
1.
#40
0.
#50
1.
#60
0.
#70
b101101 -
b101101 4
b101101 ,
1.
b1 l
b1000000000000 2
b10000000000000000000000000000011 k
#80
0.
#90
1.
#100
0.
#110
1.
#120
0.
#130
1.
#140
0.
#150
1.
#160
0.
#170
1.
#171
1/
#180
0.
#190
1?
b1 b
b101 i
b110 h
1.
#200
0.
#210
b111111 =
b1 S
b111100 L
b111100 M
1[
1.
#220
0.
#230
b0 =
b10 S
b1 T
1\
1.
#240
0.
#250
b1 =
b101 f
b101 e
bx ]
b11 S
b1 U
b10 T
1R
b100 i
b101 h
1.
#260
0.
#270
b10 =
b101 f
b101 e
bx ]
b100 S
b111101 L
b10 U
b11 T
b100 i
b101 h
1.
#280
0.
#290
b11 =
b101 f
b101 e
bx ]
b101 S
b111110 L
b11 U
b100 T
b100 i
b101 h
1.
#300
0.
#310
b100 =
b101 f
b101 e
bx ]
b110 S
b111111 L
b100 U
b101 T
b100 i
b101 h
1.
#320
0.
#330
b101 =
b101 f
b101 e
bx ]
b111 S
b0 L
b101 U
b110 T
b100 i
b101 h
1.
#340
0.
#350
b110 =
b1000 S
b1 L
b110 U
b111 T
b100 i
b101 h
1.
#360
0.
#370
b111 =
b1001 S
b10 L
b111 U
b1000 T
b100 i
b101 h
1.
#380
0.
#390
b1000 =
b1010 S
b11 L
b1000 U
b1001 T
b100 i
b101 h
1.
#400
0.
#410
b1001 =
b1011 S
b100 L
b1001 U
b1010 T
b100 i
b101 h
1.
#420
0.
#430
b1010 =
b1100 S
b101 L
b1010 U
b1011 T
b100 i
b101 h
1.
#440
0.
#450
b1011 =
b1101 S
b110 L
b1011 U
b1100 T
b100 i
b101 h
1.
#460
0.
#470
b1100 =
b1110 S
b111 L
b1100 U
b1101 T
b100 i
b101 h
1.
#480
0.
#490
b1101 =
b1111 S
b1000 L
b1101 U
b1110 T
b100 i
b101 h
1.
#500
0.
#510
b1110 =
b10000 S
b1001 L
b1110 U
b1111 T
b100 i
b101 h
1.
#520
0.
#530
b1111 =
b10001 S
b1010 L
b1111 U
b10000 T
b100 i
b101 h
1.
#540
0.
#550
b10000 =
b10010 S
b1011 L
b10000 U
b10001 T
b100 i
b101 h
1.
#560
0.
#570
b10001 =
b10011 S
b1100 L
b10001 U
b10010 T
b100 i
b101 h
1.
#580
0.
#590
b10010 =
b10100 S
b1101 L
b10010 U
b10011 T
b100 i
b101 h
1.
#600
0.
#610
b10011 =
b10101 S
b1110 L
b10011 U
b10100 T
b100 i
b101 h
1.
#620
0.
#630
b10100 =
b10110 S
b1111 L
b10100 U
b10101 T
b100 i
b101 h
1.
#640
0.
#650
b10101 =
b10111 S
b10000 L
b10101 U
b10110 T
b100 i
b101 h
1.
#660
0.
#670
b10110 =
b11000 S
b10001 L
b10110 U
b10111 T
b100 i
b101 h
1.
#680
0.
#690
b10111 =
b11001 S
b10010 L
b10111 U
b11000 T
b100 i
b101 h
1.
#700
0.
#710
b11000 =
b11010 S
b10011 L
b11000 U
b11001 T
b100 i
b101 h
1.
#720
0.
#730
b11001 =
b11011 S
b10100 L
b11001 U
b11010 T
b100 i
b101 h
1.
#740
0.
#750
b11010 =
b11100 S
b10101 L
b11010 U
b11011 T
b100 i
b101 h
1.
#760
0.
#770
b11011 =
b11101 S
b10110 L
b11011 U
b11100 T
b100 i
b101 h
1.
#780
0.
#790
b11100 =
b11110 S
b10111 L
b11100 U
b11101 T
b100 i
b101 h
1.
#800
0.
#810
b11101 =
b11111 S
b11000 L
b11101 U
b11110 T
b100 i
b101 h
1.
#820
0.
#830
b11110 =
b100000 S
b11001 L
b11110 U
b11111 T
b100 i
b101 h
1.
#840
0.
#850
b11111 =
b100001 S
b11010 L
b11111 U
b100000 T
b100 i
b101 h
1.
#860
0.
#870
b100000 =
b100010 S
b11011 L
b100000 U
b100001 T
b100 i
b101 h
1.
#880
0.
#890
b100001 =
b100011 S
b11100 L
b100001 U
b100010 T
b100 i
b101 h
1.
#900
0.
#910
b100010 =
b100100 S
b11101 L
b100010 U
b100011 T
b100 i
b101 h
1.
#920
0.
#930
b100011 =
b100101 S
b11110 L
b100011 U
b100100 T
b100 i
b101 h
1.
#940
0.
#950
b100100 =
b100110 S
b11111 L
b100100 U
b100101 T
b100 i
b101 h
1.
#960
0.
#970
b100101 =
b100111 S
b100000 L
b100101 U
b100110 T
b100 i
b101 h
1.
#980
0.
#990
b100110 =
b101000 S
b100001 L
b100110 U
b100111 T
b100 i
b101 h
1.
#1000
0.
#1010
b100111 =
b101001 S
b100010 L
b100111 U
b101000 T
b100 i
b101 h
1.
#1020
0.
#1030
b101000 =
b101010 S
b100011 L
b101000 U
b101001 T
b100 i
b101 h
1.
#1040
0.
#1050
b101001 =
b101011 S
b100100 L
b101001 U
b101010 T
b100 i
b101 h
1.
#1060
0.
#1070
b101010 =
b101100 S
b100101 L
b101010 U
b101011 T
b100 i
b101 h
1.
#1080
0.
#1090
b101011 =
b101101 S
b100110 L
b101011 U
b101100 T
b100 i
b101 h
1.
#1100
0.
#1110
b101100 =
b101110 S
b100111 L
b101100 U
b101101 T
b100 i
b101 h
1.
#1120
0.
#1130
b101101 =
b101111 S
b101000 L
b101101 U
b101110 T
b100 i
b101 h
1.
#1140
0.
#1150
b101110 =
b110000 S
b101001 L
b101110 U
b101111 T
b100 i
b101 h
1.
#1160
0.
#1170
b101111 =
b110001 S
b101010 L
b101111 U
b110000 T
b100 i
b101 h
1.
#1180
0.
#1190
b110000 =
b110010 S
b101011 L
b110000 U
b110001 T
b100 i
b101 h
1.
#1200
0.
#1210
b110001 =
b110011 S
b101100 L
b110001 U
b110010 T
b100 i
b101 h
1.
#1220
0.
#1230
b110010 =
b110100 S
b101101 L
b110010 U
b110011 T
b100 i
b101 h
1.
#1240
0.
#1250
b110011 =
b110101 S
b101110 L
b110011 U
b110100 T
b100 i
b101 h
1.
#1260
0.
#1270
b110100 =
b110110 S
b101111 L
b110100 U
b110101 T
b100 i
b101 h
1.
#1280
0.
#1290
b110101 =
b110111 S
b110000 L
b110101 U
b110110 T
b100 i
b101 h
1.
#1300
0.
#1310
b110110 =
b111000 S
b110001 L
b110110 U
b110111 T
b100 i
b101 h
1.
#1320
0.
#1330
b110111 =
b111001 S
b110010 L
b110111 U
b111000 T
b100 i
b101 h
1.
#1340
0.
#1350
b111000 =
b111010 S
b110011 L
b111000 U
b111001 T
b100 i
b101 h
1.
#1360
0.
#1370
b111001 =
b111011 S
b110100 L
b111001 U
b111010 T
b100 i
b101 h
1.
#1380
0.
#1390
b111010 =
b111100 S
b110101 L
b111010 U
b111011 T
b100 i
b101 h
1.
#1400
0.
#1410
b111011 =
b111101 S
b110110 L
b111011 U
b111100 T
b100 i
b101 h
1.
#1420
0.
#1430
b111100 =
b111110 S
b110111 L
b111100 U
b111101 T
b100 i
b101 h
1.
#1440
0.
#1450
b111101 =
b111111 S
b111000 L
b111101 U
b111110 T
b100 i
b101 h
1.
#1460
0.
#1470
b111110 =
b1000000 S
b111001 L
b111110 U
b111111 T
b100 i
b101 h
1.
#1480
0.
#1490
b111111 =
b1000001 S
b111010 L
b111111 U
b1000000 T
b100 i
b101 h
1.
#1500
0.
#1510
b0 =
b1000010 S
b111011 L
b1000000 U
b1000001 T
b100 i
b101 h
1.
#1520
0.
#1530
b1 =
b1000011 S
b111100 L
b1000001 U
b1000010 T
b100 i
b101 h
1.
#1540
0.
#1550
b111110 =
b111111 <
b0 S
b1 V
b111101 L
b1000010 U
b1000011 T
b100 i
b101 h
1.
#1560
0.
#1570
b111111 =
b1 S
b111110 L
b1000011 U
b0 T
b1 W
b100 i
b101 h
1.
#1580
0.
#1590
b0 =
b10 S
b111111 L
b0 U
b1 T
b1 X
b100 i
b101 h
1.
#1600
0.
#1610
b1 =
b101 f
b101 e
bx ]
b11 S
b111100 L
b1 U
b10 T
b111101 M
b100 i
b101 h
1.
#1620
0.
#1630
b10 =
b101 f
b101 e
bx ]
b100 S
b111101 L
b10 U
b11 T
b100 i
b101 h
1.
#1640
0.
#1650
b11 =
b101 f
b101 e
bx ]
b101 S
b111110 L
b11 U
b100 T
b100 i
b101 h
1.
#1660
0.
